xclone/__init__.py
xclone/_config.py
xclone/_logging.py
xclone/analysis/__init__.py
xclone/analysis/_clustering.py
xclone/analysis/_quickanalysis.py
xclone/analysis/_spatial.py
xclone/analysis/benchmark.py
xclone/analysis/evaluation.py
xclone/analysis/extract.py
xclone/analysis/utils.py
xclone/data/__init__.py
xclone/data/anno_data/annotate_blocks_hg19.txt
xclone/data/anno_data/annotate_blocks_hg19_update.txt
xclone/data/anno_data/annotate_blocks_hg38.txt
xclone/data/anno_data/annotate_blocks_hg38_update.txt
xclone/data/anno_data/annotate_genes_hg19_update.txt
xclone/data/anno_data/annotate_genes_hg38_select.txt
xclone/data/anno_data/annotate_genes_hg38_update.txt
xclone/data/anno_data/annotate_genes_mm10.txt
xclone/data/anno_data/cellcycle_genes.txt
xclone/data/anno_data/housekeeping_genes.txt
xclone/data/demo_datasets/__init__.py
xclone/data/demo_datasets/_datasets.py
xclone/model/HMM_BB.py
xclone/model/HMM_NB.py
xclone/model/HMM_base.py
xclone/model/XClone_combine.py
xclone/model/_BAF.py
xclone/model/_BAF_base.py
xclone/model/_BAF_process.py
xclone/model/_Gaussian_mixture.py
xclone/model/_HMM.py
xclone/model/_RDR_CNVratio.py
xclone/model/_RDR_base.py
xclone/model/_RDR_cnv.py
xclone/model/_RDR_dispersion.py
xclone/model/_RDR_gaussian_HMM.py
xclone/model/_RDR_gaussian_base.py
xclone/model/_RDR_libratio.py
xclone/model/_RDR_process.py
xclone/model/_RDR_smoothing.py
xclone/model/__init__.py
xclone/model/_denoise.py
xclone/model/_deprecated/VB/XClone_VB_base.py
xclone/model/_deprecated/VB/XClone_VB_model.py
xclone/model/_deprecated/XClone_combine.py
xclone/model/_deprecated/_RDR_discard_fucntions.py
xclone/model/_deprecated/_RDR_test.py
xclone/model/_deprecated/final_res.py
xclone/model/_deprecated/generate_emm_test.py
xclone/model/analysis_utils.py
xclone/model/base_utils.py
xclone/model/data_base_utils.py
xclone/model/diploid.py
xclone/model/mixture.py
xclone/model/phasing.py
xclone/model/smoothing.py
xclone/model/utils.py
xclone/model/xclone_baf_wrap.py
xclone-0.4.0.dist-info/METADATA
xclone-0.4.0.dist-info/WHEEL
xclone-0.4.0.dist-info/licenses/LICENSE
xclone-0.4.0.dist-info/RECORD
