Metadata-Version: 2.4
Name: xclone
Version: 0.4.0
Summary: XClone: Inference of clonal Copy Number Alterations in single cells
License-File: LICENSE
Author: Rongting Huang
Author-email: rthuang@connect.hku.hk
Requires-Python: >=3.9,<4.0
Classifier: Programming Language :: Python :: 3
Classifier: Programming Language :: Python :: 3.9
Classifier: Programming Language :: Python :: 3.10
Classifier: Programming Language :: Python :: 3.11
Classifier: Programming Language :: Python :: 3.12
Classifier: Programming Language :: Python :: 3.13
Classifier: Programming Language :: Python :: 3.14
Requires-Dist: anndata (>=0.10.7,<0.11.0)
Requires-Dist: h5py (>=3.11.0,<4.0.0)
Requires-Dist: importlib-metadata (>=7.1.0,<8.0.0)
Requires-Dist: matplotlib (>=3.9.0,<4.0.0)
Requires-Dist: numpy (>=1.26.4,<2.0.0)
Requires-Dist: palettable (>=3.3.3,<4.0.0)
Requires-Dist: pandas (>=2.2.2,<3.0.0)
Requires-Dist: requests (>=2.32.3,<3.0.0)
Requires-Dist: scanpy (>=1.10.1,<2.0.0)
Requires-Dist: scipy (>=1.13.1,<2.0.0)
Requires-Dist: squidpy (>=1.5.0,<2.0.0)
Requires-Dist: statsmodels (>=0.14.2,<0.15.0)
